spinlab/__init__.py
spinlab/version.py
spinlab/analysis/__init__.py
spinlab/analysis/peaks.py
spinlab/analysis/relaxation_fit.py
spinlab/analysis/simulate_enhancement_profiles.py
spinlab/config/__init__.py
spinlab/config/config.py
spinlab/config/spinlab.cfg
spinlab/constants/__init__.py
spinlab/constants/constants.py
spinlab/constants/mrProperties.py
spinlab/constants/radicalProperties.py
spinlab/core/__init__.py
spinlab/core/base.py
spinlab/core/coord.py
spinlab/core/data.py
spinlab/core/ufunc.py
spinlab/core/util.py
spinlab/fitting/__init__.py
spinlab/fitting/general.py
spinlab/io/__init__.py
spinlab/io/bes3t.py
spinlab/io/cnsi.py
spinlab/io/delta.py
spinlab/io/h5.py
spinlab/io/load.py
spinlab/io/load_csv.py
spinlab/io/logs.py
spinlab/io/mat.py
spinlab/io/power.py
spinlab/io/prospa.py
spinlab/io/random.py
spinlab/io/rs2d.py
spinlab/io/save.py
spinlab/io/specman.py
spinlab/io/tnmr.py
spinlab/io/topspin.py
spinlab/io/vna.py
spinlab/io/vnmrj.py
spinlab/io/winepr.py
spinlab/math/__init__.py
spinlab/math/lineshape.py
spinlab/math/pulses.py
spinlab/math/relaxation.py
spinlab/math/window.py
spinlab/plotting/__init__.py
spinlab/plotting/colors.py
spinlab/plotting/general.py
spinlab/plotting/image.py
spinlab/plotting/stack_plot.py
spinlab/processing/__init__.py
spinlab/processing/align.py
spinlab/processing/apodization.py
spinlab/processing/average.py
spinlab/processing/conversion.py
spinlab/processing/fft.py
spinlab/processing/helpers.py
spinlab/processing/integration.py
spinlab/processing/interpolation.py
spinlab/processing/offset.py
spinlab/processing/phase.py
spinlab/reporting/__init__.py
spinlab/widgets/__init__.py
spinlab/widgets/align_widget.py
spinlab/widgets/phase_widget.py
spinlab-1.1.3.dist-info/licenses/LICENSE.txt
spinlab-1.1.3.dist-info/METADATA
spinlab-1.1.3.dist-info/WHEEL
spinlab-1.1.3.dist-info/top_level.txt
spinlab-1.1.3.dist-info/RECORD
