Metadata-Version: 2.4
Name: spinlab
Version: 1.1.3
Summary: SpinLab - Bringing the Power of Python to MR Spectroscopy
License-Expression: MIT
Keywords: ODNP,DNP,Spin,NMR,EPR,ESR
Classifier: Development Status :: 3 - Alpha
Classifier: Programming Language :: Python :: 3.10
Classifier: Programming Language :: Python :: 3.11
Classifier: Programming Language :: Python :: 3.12
Requires-Python: >=3.10
License-File: LICENSE.txt
Requires-Dist: numpy>=2.0.0
Requires-Dist: scipy>=1.14.0
Requires-Dist: matplotlib>=3.9.0
Requires-Dist: h5py>=3.11.0
Dynamic: license-file
